cobrastyle/__init__.py
cobrastyle/constants.py
cobrastyle/clients/__init__.py
cobrastyle/clients/base.py
cobrastyle/clients/lambda_client.py
cobrastyle/runtimes/__init__.py
cobrastyle/runtimes/abstracts.py
cobrastyle/runtimes/lambda_runtime.py
cobrastyle/runtimes/models.py
cobrastyle-0.0.3.dist-info/LICENSE
cobrastyle-0.0.3.dist-info/METADATA
cobrastyle-0.0.3.dist-info/WHEEL
cobrastyle-0.0.3.dist-info/top_level.txt
cobrastyle-0.0.3.dist-info/RECORD
